z3c.wizard-2.0-py3.9-nspkg.pth
z3c/wizard/README.rst
z3c/wizard/__init__.py
z3c/wizard/browser.zcml
z3c/wizard/button.py
z3c/wizard/configure.zcml
z3c/wizard/interfaces.py
z3c/wizard/meta.zcml
z3c/wizard/step.pt
z3c/wizard/step.py
z3c/wizard/testing.py
z3c/wizard/tests.py
z3c/wizard/wizard.pt
z3c/wizard/wizard.py
z3c/wizard/zcml.py
z3c/wizard/zcml.rst
z3c.wizard-2.0.dist-info/LICENSE.txt
z3c.wizard-2.0.dist-info/METADATA
z3c.wizard-2.0.dist-info/WHEEL
z3c.wizard-2.0.dist-info/namespace_packages.txt
z3c.wizard-2.0.dist-info/top_level.txt
z3c.wizard-2.0.dist-info/RECORD
