Metadata-Version: 2.1
Name: z3c.wizard
Version: 2.0
Summary: Wizard based on z3c.form for for Zope3
Home-page: https://github.com/zopefoundation/z3c.wizard
Author: Roger Ineichen and the Zope Community
Author-email: zope-dev@zope.dev
License: ZPL 2.1
Keywords: zope zope3 z3c form wizard
Classifier: Development Status :: 4 - Beta
Classifier: Environment :: Web Environment
Classifier: Intended Audience :: Developers
Classifier: License :: OSI Approved :: Zope Public License
Classifier: Programming Language :: Python :: 3
Classifier: Programming Language :: Python :: 3.7
Classifier: Programming Language :: Python :: 3.8
Classifier: Programming Language :: Python :: 3.9
Classifier: Programming Language :: Python :: 3.10
Classifier: Programming Language :: Python :: 3.11
Classifier: Programming Language :: Python :: Implementation :: CPython
Classifier: Programming Language :: Python :: Implementation :: PyPy
Classifier: Natural Language :: English
Classifier: Operating System :: OS Independent
Classifier: Topic :: Internet :: WWW/HTTP
Classifier: Framework :: Zope :: 3
Requires-Python: >=3.7
License-File: LICENSE.txt
Requires-Dist: setuptools
Requires-Dist: z3c.form (>=2.0)
Requires-Dist: z3c.formui
Requires-Dist: z3c.pagelet
Requires-Dist: zope.browserpage
Requires-Dist: zope.component
Requires-Dist: zope.configuration
Requires-Dist: zope.event
Requires-Dist: zope.i18nmessageid
Requires-Dist: zope.interface
Requires-Dist: zope.lifecycleevent
Requires-Dist: zope.location
Requires-Dist: zope.publisher
Requires-Dist: zope.schema
Requires-Dist: zope.security
Requires-Dist: zope.traversing
Provides-Extra: test
Requires-Dist: z3c.macro ; extra == 'test'
Requires-Dist: zope.app.pagetemplate ; extra == 'test'
Requires-Dist: zope.app.testing ; extra == 'test'
Requires-Dist: zope.browserresource ; extra == 'test'
Requires-Dist: zope.publisher ; extra == 'test'
Requires-Dist: zope.testing ; extra == 'test'
Requires-Dist: zope.testrunner ; extra == 'test'
